holo_vector_store/__about__.py
holo_vector_store/__init__.py
holo_vector_store/holo_vector_store.py
holo_vector_store/hologres_wrapper.py
holo_vector_store-0.0.8.dist-info/METADATA
holo_vector_store-0.0.8.dist-info/WHEEL
holo_vector_store-0.0.8.dist-info/licenses/LICENSE.txt
holo_vector_store-0.0.8.dist-info/RECORD
