Metadata-Version: 2.1
Name: holo-vector-store
Version: 0.0.8
Project-URL: Documentation, https://github.com/unknown/holo-vector-store#readme
Project-URL: Issues, https://github.com/unknown/holo-vector-store/issues
Project-URL: Source, https://github.com/unknown/holo-vector-store
Author-email: Changgeng Zhao <zhaochanggeng.zcg@alibaba-inc.com>
License-Expression: MIT
License-File: LICENSE.txt
Classifier: Development Status :: 4 - Beta
Classifier: Programming Language :: Python
Classifier: Programming Language :: Python :: 3.7
Classifier: Programming Language :: Python :: 3.8
Classifier: Programming Language :: Python :: 3.9
Classifier: Programming Language :: Python :: 3.10
Classifier: Programming Language :: Python :: 3.11
Classifier: Programming Language :: Python :: Implementation :: CPython
Classifier: Programming Language :: Python :: Implementation :: PyPy
Requires-Python: >=3.7
Requires-Dist: psycopg2-binary
Requires-Dist: typing
Requires-Dist: uuid
